isisdl/__init__.py
isisdl/__main__.py
isisdl/autorun.py
isisdl/compress.py
isisdl/settings.py
isisdl/utils.py
isisdl/version.py
isisdl/backend/__init__.py
isisdl/backend/config.py
isisdl/backend/crypt.py
isisdl/backend/database_helper.py
isisdl/backend/request_helper.py
isisdl/backend/status.py
isisdl/backend/sync_database.py
isisdl/resources/changelog/1.3/1.3.13.md
isisdl/resources/changelog/1.3/1.3.14.md
isisdl/resources/changelog/1.3/1.3.16.md
isisdl/resources/changelog/1.3/1.3.17.md
isisdl/resources/changelog/1.3/1.3.18.md
isisdl/resources/changelog/1.3/1.3.19.md
isisdl/resources/changelog/1.4/1.4.0.md
isisdl/resources/completions/bash/bash_isisdl
isisdl/resources/completions/fish/gitdummy
isisdl/resources/completions/zsh/_isisdl
isisdl/resources/manpages/isisdl.1
isisdl-1.3.20.dist-info/LICENSE
isisdl-1.3.20.dist-info/METADATA
isisdl-1.3.20.dist-info/WHEEL
isisdl-1.3.20.dist-info/entry_points.txt
isisdl-1.3.20.dist-info/top_level.txt
isisdl-1.3.20.dist-info/RECORD
