Metadata-Version: 2.1
Name: isisdl
Version: 1.3.20
Summary: Download *everything* from ISIS - with _speed_
Author: Emily Seebeck
License: GPL3
Platform: unix
Platform: linux
Platform: osx
Platform: cygwin
Platform: win32
Classifier: Programming Language :: Python :: 3
Classifier: Programming Language :: Python :: 3 :: Only
Classifier: Programming Language :: Python :: 3.8
Classifier: Programming Language :: Python :: 3.9
Classifier: Programming Language :: Python :: 3.10
Requires-Python: >=3.8
License-File: LICENSE
Requires-Dist: cryptography ~=38.0.4
Requires-Dist: requests ~=2.28.1
Requires-Dist: PyYAML ~=6.0
Requires-Dist: packaging ~=22.0
Requires-Dist: colorama ~=0.4.6
Requires-Dist: distro ~=1.8.0
Requires-Dist: psutil ~=5.9.4
Requires-Dist: pyinotify ~=0.9.6 ; platform_system == "Linux"
Provides-Extra: testing
Requires-Dist: pytest ~=6.2.5 ; extra == 'testing'
Requires-Dist: pytest-cov ~=2.12.1 ; extra == 'testing'
Requires-Dist: mypy ~=0.910 ; extra == 'testing'
Requires-Dist: flake8 ~=3.9.2 ; extra == 'testing'
Requires-Dist: tox ~=3.24.3 ; extra == 'testing'
Requires-Dist: types-requests ~=2.28.11.5 ; extra == 'testing'
Requires-Dist: types-PyYAML ~=6.0.12.2 ; extra == 'testing'
Requires-Dist: types-colorama ~=0.4.15 ; extra == 'testing'
Requires-Dist: types-psutil ~=5.9.5 ; extra == 'testing'
Requires-Dist: twine ~=4.0.2 ; extra == 'testing'
Requires-Dist: build ~=0.9.0 ; extra == 'testing'
Requires-Dist: radon ~=5.1.0 ; extra == 'testing'
Requires-Dist: setuptools ~=69.0.3 ; extra == 'testing'
Requires-Dist: matplotlib ~=3.7.4 ; extra == 'testing'
